django_file_form/__init__.py
django_file_form/admin.py
django_file_form/conf.py
django_file_form/django_util.py
django_file_form/fields.py
django_file_form/forms.py
django_file_form/model_admin.py
django_file_form/model_manager.py
django_file_form/models.py
django_file_form/type_util.py
django_file_form/uploaded_file.py
django_file_form/urls.py
django_file_form/util.py
django_file_form/ajaxuploader/__init__.py
django_file_form/management/__init__.py
django_file_form/management/commands/__init__.py
django_file_form/management/commands/delete_unused_files.py
django_file_form/migrations/0001_initial.py
django_file_form/migrations/0002_auto_20170316_0901.py
django_file_form/migrations/0003_auto_20170317_1230.py
django_file_form/migrations/0004_auto_20170423_0329.py
django_file_form/migrations/0005_auto_20200407_0814.py
django_file_form/migrations/0006_auto_20200501_0908.py
django_file_form/migrations/0007_auto_20210119_0104.py
django_file_form/migrations/0008_auto_20220519_0204.py
django_file_form/migrations/0009_rename_temporaryuploadedfile_form_id_field_name_form_id_field_name_idx.py
django_file_form/migrations/__init__.py
django_file_form/s3_multipart/__init__.py
django_file_form/s3_multipart/urls.py
django_file_form/s3_multipart/utils.py
django_file_form/s3_multipart/views.py
django_file_form/static/file_form/auto_init.js
django_file_form/static/file_form/file_form.css
django_file_form/static/file_form/file_form.js
django_file_form/static/file_form/file_form.js.map
django_file_form/static/file_form/file_form.min.js
django_file_form/static/file_form/file_form.min.js.map
django_file_form/templates/django_file_form/admin_change_form.html
django_file_form/templates/django_file_form/upload_widget.html
django_file_form/tus/__init__.py
django_file_form/tus/urls.py
django_file_form/tus/utils.py
django_file_form/tus/views.py
django_file_form/widgets/__init__.py
django_file_form/widgets/base_upload_widget.py
django_file_form/widgets/form_data.py
django_file_form-4.0.0.dist-info/licenses/LICENSE.rst
django_file_form-4.0.0.dist-info/METADATA
django_file_form-4.0.0.dist-info/WHEEL
django_file_form-4.0.0.dist-info/top_level.txt
django_file_form-4.0.0.dist-info/RECORD
